README.txt
setup.cfg
setup.py
adsense.portlet.egg-info/PKG-INFO
adsense.portlet.egg-info/SOURCES.txt
adsense.portlet.egg-info/dependency_links.txt
adsense.portlet.egg-info/entry_points.txt
adsense.portlet.egg-info/namespace_packages.txt
adsense.portlet.egg-info/nav_portlet.py
adsense.portlet.egg-info/not-zip-safe
adsense.portlet.egg-info/requires.txt
adsense.portlet.egg-info/top_level.txt
wwp/__init__.py
wwp/adsense/__init__.py
wwp/adsense/portlet/__init__.py
wwp/adsense/portlet/wwp_adsense.py
wwp/adsense/portlet/tests/__init__.py
wwp/adsense/portlet/tests/base.py
wwp/adsense/portlet/tests/test_portlet.py