Metadata-Version: 1.0
Name: adsense.portlet
Version: 1.0dev
Summary: Display adsense zones from google
Home-page: http://wwp.greenwichmeantime.com
Author: Peter Dyson
Author-email: pjdyson@gmail.com
License: GPL
Keywords: WWP wwp adverts advertising adsense google plone zope
Platform: UNKNOWN
Classifier: Framework :: Plone
Classifier: Programming Language :: Python
Classifier: Topic :: Software Development :: Libraries :: Python Modules
